LICENSE.txt
MANIFEST.in
README.md
requirements.txt
setup.cfg
setup.py
tqcli/__init__.py
tqcli/tqcli.py
tqcli.egg-info/PKG-INFO
tqcli.egg-info/SOURCES.txt
tqcli.egg-info/dependency_links.txt
tqcli.egg-info/entry_points.txt
tqcli.egg-info/pbr.json
tqcli.egg-info/requires.txt
tqcli.egg-info/top_level.txt
tqcli.egg-info/zip-safe
tqcli/batch/__init__.py
tqcli/batch/file_manager.py
tqcli/batch/server_handler.py
tqcli/config/__init__.py
tqcli/config/config.py